goss_config_gen/__init__.py
goss_config_gen/cli.py
goss_config_gen/config.py
goss_config_gen/exceptions.py
goss_config_gen/role_import.py
goss_config_gen/utils.py
goss_config_gen-1.3.0.dist-info/METADATA
goss_config_gen-1.3.0.dist-info/WHEEL
goss_config_gen-1.3.0.dist-info/entry_points.txt
goss_config_gen-1.3.0.dist-info/top_level.txt
goss_config_gen-1.3.0.dist-info/RECORD
