Metadata-Version: 2.1
Name: goss-config-gen
Version: 1.3.0
Summary: Generate Gossamer config files and AWS aliases
Home-page: https://github.com/GESkunkworks/goss-config-gen
Author: Michael Palmer
Author-email: github@michaeldpalmer.com
License: UNKNOWN
Keywords: gossamer config aws
Platform: UNKNOWN
Classifier: Programming Language :: Python :: 2.7
Classifier: Programming Language :: Python :: 3.6
Classifier: Development Status :: 5 - Production/Stable
Classifier: Topic :: Utilities
Requires-Dist: setuptools-scm (~=3.1.0)
Requires-Dist: six (~=1.11.0)
